pyserpent/__init__.py
pyserpent/serpent.py
pyserpent-1.0.0.dist-info/licenses/LICENSE
pyserpent-1.0.0.dist-info/METADATA
pyserpent-1.0.0.dist-info/WHEEL
pyserpent-1.0.0.dist-info/top_level.txt
pyserpent-1.0.0.dist-info/RECORD
